cryptly/__init__.py
cryptly/affine.py
cryptly-0.1.1.dist-info/LICENSE
cryptly-0.1.1.dist-info/METADATA
cryptly-0.1.1.dist-info/WHEEL
cryptly-0.1.1.dist-info/top_level.txt
cryptly-0.1.1.dist-info/RECORD
