Metadata-Version: 2.1
Name: cryptly
Version: 0.1.1
Summary: A Python library implementing common encryption and cipher techniques, providing easy-to-use functions for encryption and decryption.
Author-email: Ubaid Ur Rehman <rehmanubaid2003@gmail.com>
Project-URL: Homepage, https://github.com/ubaidrmn/cryptly
Project-URL: Issues, https://github.com/ubaidrmn/cryptly/issues
Classifier: Programming Language :: Python :: 3
Classifier: License :: OSI Approved :: MIT License
Classifier: Operating System :: OS Independent
Requires-Python: >=3.0
License-File: LICENSE
